mad_hack_calc/__init__.py
mad_hack_calc-0.0.1.dist-info/LICENCE.txt
mad_hack_calc-0.0.1.dist-info/METADATA
mad_hack_calc-0.0.1.dist-info/WHEEL
mad_hack_calc-0.0.1.dist-info/top_level.txt
mad_hack_calc-0.0.1.dist-info/RECORD
