Metadata-Version: 2.1
Name: mad-hack-calc
Version: 0.0.1
Summary: Simpe calc
Home-page: UNKNOWN
Author: Madhankumar
Author-email: UNKNOWN
License: UNKNOWN
Platform: UNKNOWN
Classifier: Programming Language :: Python :: 3
Classifier: License :: OSI Approved :: MIT License
Classifier: Operating System :: OS Independent
